setup.py
datebar/__init__.py
datebar/date_bar.py
datebar.egg-info/PKG-INFO
datebar.egg-info/SOURCES.txt
datebar.egg-info/dependency_links.txt
datebar.egg-info/entry_points.txt
datebar.egg-info/top_level.txt