Metadata-Version: 1.0
Name: datebar
Version: 0.0.7
Summary: Show a bar to display the progress of the year
Home-page: https://github.com/Neulana/datebar
Author: neulana
Author-email: fupinyou@gmail.com
License: MIT Licence
Platform: UNKNOWN
